cleanvoice/__init__.py
cleanvoice/convtasnet.onnx
cleanvoice-0.0.2.dist-info/METADATA
cleanvoice-0.0.2.dist-info/WHEEL
cleanvoice-0.0.2.dist-info/top_level.txt
cleanvoice-0.0.2.dist-info/RECORD
