Metadata-Version: 2.1
Name: cleanvoice
Version: 0.0.2
Summary: A Fast Speech Enhancement toolkit using Conv-TasNet
Home-page: https://github.com/seanghay/cleanvoice
Author: Seanghay Yath
Author-email: seanghay.dev@gmail.com
License: MIT
Classifier: Programming Language :: Python :: 3
Classifier: Operating System :: OS Independent
Classifier: Intended Audience :: Developers
Classifier: Natural Language :: English
Requires-Python: >3.5
Requires-Dist: onnxruntime
Requires-Dist: librosa
Requires-Dist: numpy
